setup.py
steam_game_scale/README.md
steam_game_scale/__init__.py
steam_game_scale/__main__.py
steam_game_scale/api.py
steam_game_scale/game.py
steam_game_scale/player.py
steam_game_scale/scale.py
steam_game_scale/steam_game_scale.png
steam_game_scale/steam_game_scale.py
steam_game_scale/url_images.py
steam_game_scale.egg-info/PKG-INFO
steam_game_scale.egg-info/SOURCES.txt
steam_game_scale.egg-info/dependency_links.txt
steam_game_scale.egg-info/entry_points.txt
steam_game_scale.egg-info/requires.txt
steam_game_scale.egg-info/top_level.txt