Metadata-Version: 1.0
Name: steam_game_scale
Version: 1.0.12
Summary: Compare your Steam game playtime against your friends
Home-page: https://github.com/knbnnate/steam_game_scale/
Author: Nate Campbell
Author-email: nathanc@alum.bu.edu
License: UNKNOWN
Keywords: steam api friends
Platform: UNKNOWN
